{  
   "_phoneTypeLookupID":{  
      "label":"Phone number type",
      "placeholder":"",
      "collWidth":12
   },
   "_phonePre":{  
      "label":"Phone number (Pre, car, cdr, ext)",
      "placeholder":"Phone pre",
      "collWidth":4
   },
   "_phoneCar":{  
      "label":"",
      "placeholder":"Phone car",
      "collWidth":8
   },
   "_phoneCdr":{  
      "label":"",
      "placeholder":"Phone cdr",
      "collWidth":8
   },
   "_phoneExt":{  
      "label":"",
      "placeholder":"Phone ext",
      "collWidth":4
   },
   "firstName":{  
      "label":"",
      "placeholder":"First name",
      "collWidth":6
   },
   "middleName":{  
      "label":"",
      "placeholder":"Middle name",
      "collWidth":6
   },
   "lastName":{  
      "label":"",
      "placeholder":"Last name",
      "collWidth":6
   },
   "suffix":{  
      "label":"",
      "placeholder":"Suffix",
      "collWidth":6
   },
   "email":{  
      "label":"",
      "placeholder":"E-mail",
      "collWidth":12
   },
   "employer":{  
      "label":"",
      "placeholder":"Employer",
      "collWidth":12
   },
   "addraddressTypeLookupID":{  
      "label":"Address type",
      "placeholder":"",
      "collWidth":12
   },
   "addrstreet1":{  
      "label":"",
      "placeholder":"Address 1",
      "collWidth":12
   },
   "addrstreet2":{  
      "label":"",
      "placeholder":"Address 2",
      "collWidth":12
   },
   "addrcity":{  
      "label":"",
      "placeholder":"City",
      "collWidth":6
   },
   "addrstate":{  
      "label":"",
      "placeholder":"",
      "collWidth":3
   },
   "addrzip":{  
      "label":"",
      "placeholder":"ZIP",
      "collWidth":3
   }
}